sdbus_async/notifications/__init__.py
sdbus_async/notifications/py.typed
sdbus_block/notifications/__init__.py
sdbus_block/notifications/py.typed
sdbus_notifications-1.0.3.dist-info/COPYING
sdbus_notifications-1.0.3.dist-info/COPYING.LESSER
sdbus_notifications-1.0.3.dist-info/METADATA
sdbus_notifications-1.0.3.dist-info/WHEEL
sdbus_notifications-1.0.3.dist-info/top_level.txt
sdbus_notifications-1.0.3.dist-info/RECORD
