Metadata-Version: 2.1
Name: sdbus-notifications
Version: 1.0.3
Summary: Freedesktop notifications binds for sdbus.
Home-page: https://github.com/python-sdbus/python-sdbus-notifications
Author: igo95862
Author-email: igo95862@yandex.ru
License: LGPL-2.1-or-later
Project-URL: Documentation, https://python-sdbus-notifications.readthedocs.io/en/latest/
Project-URL: Source, https://github.com/python-sdbus/python-sdbus-notifications
Project-URL: Tracker, https://github.com/python-sdbus/python-sdbus-notifications/issues
Keywords: dbus notifications linux freedesktop
Classifier: Development Status :: 5 - Production/Stable
Classifier: Intended Audience :: Developers
Classifier: License :: OSI Approved :: GNU Lesser General Public License v2 or later (LGPLv2+)
Classifier: Operating System :: POSIX :: Linux
Classifier: Programming Language :: Python :: 3 :: Only
Classifier: Topic :: Software Development :: Libraries :: Python Modules
Requires-Python: >=3.7
License-File: COPYING
License-File: COPYING.LESSER
Requires-Dist: sdbus>=0.8rc2
